{"enableComments":false,"objectRelationships":[{"parameterObjectFieldName":"","parameterObjectFieldId":0,"label":{"en_US":"requestor"},"reverse":false,"type":"oneToMany","name":"case","deletionType":"prevent","objectDefinitionExternalReferenceCode1":"8372b83e-d675-46b8-13be-36eb5a39ecf0","objectDefinitionExternalReferenceCode2":"5bcf4c9a-4bb5-e281-c25b-e8400a6b4b25","objectDefinitionName2":"Case"}],"enableCategorization":true,"accountEntryRestrictedObjectFieldName":"","objectActions":[],"accountEntryRestricted":false,"externalReferenceCode":"8372b83e-d675-46b8-13be-36eb5a39ecf0","objectFields":[{"indexed":false,"objectFieldSettings":[],"readOnly":"true","DBType":"String","label":{"en_US":"Author"},"type":"String","required":false,"externalReferenceCode":"cd03d88d-7f15-4df5-1662-e4576549d810","indexedAsKeyword":false,"system":true,"indexedLanguageId":"","name":"creator","state":false,"businessType":"Text","readOnlyConditionExpression":""},{"indexed":false,"objectFieldSettings":[],"readOnly":"true","DBType":"Date","label":{"en_US":"Create Date"},"type":"Date","required":false,"externalReferenceCode":"99c47ffd-ea48-8df0-87cf-819a8eec4b6b","indexedAsKeyword":false,"system":true,"indexedLanguageId":"","name":"createDate","state":false,"businessType":"Date","readOnlyConditionExpression":""},{"indexed":false,"objectFieldSettings":[],"readOnly":"false","DBType":"String","label":{"en_US":"External Reference Code"},"type":"String","required":false,"externalReferenceCode":"222aa5b7-c0aa-7d62-10b9-9f06773b5007","indexedAsKeyword":false,"system":true,"indexedLanguageId":"","name":"externalReferenceCode","state":false,"businessType":"Text","readOnlyConditionExpression":""},{"indexed":true,"objectFieldSettings":[],"readOnly":"true","DBType":"Long","label":{"en_US":"ID"},"type":"Long","required":false,"externalReferenceCode":"08bcc19c-f433-4db5-7282-fc177f40abf2","indexedAsKeyword":true,"system":true,"indexedLanguageId":"","name":"id","state":false,"businessType":"LongInteger","readOnlyConditionExpression":""},{"indexed":false,"objectFieldSettings":[],"readOnly":"true","DBType":"Date","label":{"en_US":"Modified Date"},"type":"Date","required":false,"externalReferenceCode":"3f65e0f6-68b2-d9d6-4cbb-68ceb4f56d2f","indexedAsKeyword":false,"system":true,"indexedLanguageId":"","name":"modifiedDate","state":false,"businessType":"Date","readOnlyConditionExpression":""},{"indexed":false,"objectFieldSettings":[],"readOnly":"true","DBType":"String","label":{"en_US":"Status"},"type":"String","required":false,"externalReferenceCode":"dae75b82-9621-cfa9-b7fb-f80d4aebdf4a","indexedAsKeyword":false,"system":true,"indexedLanguageId":"","name":"status","state":false,"businessType":"Text","readOnlyConditionExpression":""},{"indexed":true,"objectFieldSettings":[],"readOnly":"false","DBType":"String","label":{"en_US":"Name"},"type":"String","required":true,"externalReferenceCode":"3846d476-a96f-3230-4cf5-fb0afdb8771e","indexedAsKeyword":false,"system":false,"indexedLanguageId":"en_US","name":"name","state":false,"businessType":"Text","readOnlyConditionExpression":""},{"indexed":true,"objectFieldSettings":[],"readOnly":"false","DBType":"String","label":{"en_US":"Address"},"type":"String","required":false,"externalReferenceCode":"44b40387-00f2-daac-d53b-6da489ef3073","indexedAsKeyword":false,"system":false,"indexedLanguageId":"en_US","name":"address","state":false,"businessType":"Text","readOnlyConditionExpression":""},{"indexed":true,"objectFieldSettings":[],"readOnly":"false","DBType":"String","label":{"en_US":"company"},"type":"String","required":true,"externalReferenceCode":"25ae1975-9a9c-e14a-f090-8cdc55d7a316","indexedAsKeyword":false,"system":false,"indexedLanguageId":"en_US","name":"company","state":false,"businessType":"Text","readOnlyConditionExpression":""}],"restContextPath":"/o/c/requestors","scope":"company","portlet":true,"parameterRequired":false,"enableObjectEntryHistory":false,"titleObjectFieldName":"name","objectValidationRules":[],"active":true,"defaultLanguageId":"en_US","label":{"en_US":"Requestor"},"panelCategoryKey":"control_panel.object","pluralLabel":{"en_US":"Requestors"},"objectLayouts":[],"system":false,"objectViews":[],"name":"Requestor","actions":{"permissions":{},"get":{},"update":{},"delete":{}},"status":{"label_i18n":"Approved","code":0,"label":"approved"}}